pyGWRetrieval/__init__.py
pyGWRetrieval/cli.py
pyGWRetrieval/parallel.py
pyGWRetrieval/retrieval.py
pyGWRetrieval/spatial.py
pyGWRetrieval/temporal.py
pyGWRetrieval/utils.py
pyGWRetrieval/visualization.py
pygwretrieval-0.1.0.dist-info/licenses/LICENSE
pygwretrieval-0.1.0.dist-info/METADATA
pygwretrieval-0.1.0.dist-info/WHEEL
pygwretrieval-0.1.0.dist-info/entry_points.txt
pygwretrieval-0.1.0.dist-info/top_level.txt
pygwretrieval-0.1.0.dist-info/RECORD
