Metadata-Version: 2.4
Name: pyGWRetrieval
Version: 0.1.0
Summary: A Python package for retrieving USGS groundwater level data
Author-email: Sayantan Majumdar <sayantan.majumdar@dri.edu>
Maintainer-email: Sayantan Majumdar <sayantan.majumdar@dri.edu>
License-Expression: MIT
Project-URL: Homepage, https://github.com/example/pyGWRetrieval
Project-URL: Documentation, https://pygwretrieval.readthedocs.io
Project-URL: Repository, https://github.com/example/pyGWRetrieval
Project-URL: Changelog, https://github.com/example/pyGWRetrieval/blob/main/CHANGELOG.md
Project-URL: Bug Tracker, https://github.com/example/pyGWRetrieval/issues
Keywords: groundwater,USGS,hydrology,water-resources,data-retrieval,NWIS,geospatial,time-series
Classifier: Development Status :: 3 - Alpha
Classifier: Intended Audience :: Science/Research
Classifier: Operating System :: OS Independent
Classifier: Programming Language :: Python :: 3
Classifier: Programming Language :: Python :: 3.8
Classifier: Programming Language :: Python :: 3.9
Classifier: Programming Language :: Python :: 3.10
Classifier: Programming Language :: Python :: 3.11
Classifier: Programming Language :: Python :: 3.12
Classifier: Topic :: Scientific/Engineering :: GIS
Classifier: Topic :: Scientific/Engineering :: Hydrology
Requires-Python: >=3.8
License-File: LICENSE
Requires-Dist: dataretrieval>=1.0.0
Requires-Dist: pandas>=1.3.0
Requires-Dist: geopandas>=0.10.0
Requires-Dist: shapely>=1.8.0
Requires-Dist: pyproj>=3.0.0
Requires-Dist: pgeocode>=0.3.0
Requires-Dist: matplotlib>=3.4.0
Requires-Dist: numpy>=1.20.0
Requires-Dist: dask>=2022.1.0
Provides-Extra: dev
Requires-Dist: pytest>=7.0.0; extra == "dev"
Requires-Dist: pytest-cov>=3.0.0; extra == "dev"
Requires-Dist: black>=22.0.0; extra == "dev"
Requires-Dist: flake8>=4.0.0; extra == "dev"
Requires-Dist: mypy>=0.950; extra == "dev"
Requires-Dist: isort>=5.10.0; extra == "dev"
Provides-Extra: docs
Requires-Dist: mkdocs>=1.5.0; extra == "docs"
Requires-Dist: mkdocs-material>=9.0.0; extra == "docs"
Requires-Dist: mkdocstrings[python]>=0.24.0; extra == "docs"
Requires-Dist: pymdown-extensions>=10.0; extra == "docs"
Provides-Extra: viz
Requires-Dist: seaborn>=0.11.0; extra == "viz"
Requires-Dist: contextily>=1.2.0; extra == "viz"
Provides-Extra: distributed
Requires-Dist: dask[distributed]>=2022.1.0; extra == "distributed"
Requires-Dist: bokeh>=2.4.0; extra == "distributed"
Provides-Extra: all
Requires-Dist: pyGWRetrieval[dev,distributed,docs,viz]; extra == "all"
Dynamic: license-file
